ssvtools/query_structure.py
ssvtools-0.1.0.dist-info/licenses/LICENSE
ssvtools-0.1.0.dist-info/METADATA
ssvtools-0.1.0.dist-info/WHEEL
ssvtools-0.1.0.dist-info/top_level.txt
ssvtools-0.1.0.dist-info/RECORD
