Metadata-Version: 2.4
Name: ssvtools
Version: 0.1.0
Summary: Python Utilities for extracting information form SPARC Subject-Specific Vagus Scaffolds using Zinc.
Author-email: Richard Christie <r.christie@auckland.ac.nz>
License-Expression: Apache-2.0
Keywords: Medical,Physiology,Anatomical,Mesh,Finite Element,SPARC,Vagus,Nerve
Classifier: Programming Language :: Python :: 3
Classifier: Operating System :: OS Independent
Requires-Python: >=3.8
License-File: LICENSE
Requires-Dist: cmlibs.maths>=0.7.2
Requires-Dist: cmlibs.utils>=0.12.5
Requires-Dist: cmlibs.zinc>=4.2.1
Dynamic: license-file
